mullvad_tool/cli.py
mullvad_tool/keypair.py
mullvad_tool/openvpn.py
mullvad_tool/portgen.py
mullvad_tool/wireguard.py
mullvad_tool-0.1.4.dist-info/LICENSE
mullvad_tool-0.1.4.dist-info/METADATA
mullvad_tool-0.1.4.dist-info/WHEEL
mullvad_tool-0.1.4.dist-info/entry_points.txt
mullvad_tool-0.1.4.dist-info/RECORD
