Metadata-Version: 2.1
Name: mullvad-tool
Version: 0.1.4
Summary: Utility to generate Mikrotik configuration scripts from Mullvad configuration files, among other things
Author: Dave Williams
Author-email: dave@dave.io
Requires-Python: >=3.10,<4.0
Classifier: Programming Language :: Python :: 3
Classifier: Programming Language :: Python :: 3.10
Classifier: Programming Language :: Python :: 3.11
Classifier: Programming Language :: Python :: 3.12
Classifier: Programming Language :: Python :: 3.13
Requires-Dist: chevron (>=0.14.0,<0.15.0)
Requires-Dist: click (>=8.1.7,<9.0.0)
Requires-Dist: cryptography (>=43.0.3,<44.0.0)
Requires-Dist: requests (>=2.32.3,<3.0.0)
Requires-Dist: wireguard-tools (>=0.5.0,<0.6.0)
